tests/__init__.py
tests/conftest.py
tests/test_nocopy.py
tests/test_prettyfier.py
tests/test_rawbytes.py
tests/test_type_identifiers.py
tests/test_types.py
tests/test_util.py
x690/__init__.py
x690/exc.py
x690/py.typed
x690/types.py
x690/util.py
x690-1.0.0.post1.dist-info/LICENSE.txt
x690-1.0.0.post1.dist-info/METADATA
x690-1.0.0.post1.dist-info/WHEEL
x690-1.0.0.post1.dist-info/top_level.txt
x690-1.0.0.post1.dist-info/RECORD
