Metadata-Version: 2.1
Name: x690
Version: 1.0.0.post1
Summary: Pure Python X.690 implementation
Home-page: https://exhuma.github.io/x690/
Author: Michel Albert
Author-email: michel@albert.lu
License: MIT
Project-URL: Bug Tracker, https://github.com/exhuma/x690/issues
Classifier: Development Status :: 5 - Production/Stable
Classifier: Intended Audience :: Developers
Classifier: License :: OSI Approved :: MIT License
Classifier: Operating System :: OS Independent
Classifier: Programming Language :: Python
Classifier: Programming Language :: Python :: 3
Classifier: Typing :: Typed
Requires-Python: >=3.7
Provides-Extra: dev
Provides-Extra: test
License-File: LICENSE.txt
